pyrogram/__init__.py
pyrogram/client.py
pyrogram/dispatcher.py
pyrogram/emoji.py
pyrogram/file_id.py
pyrogram/filters.py
pyrogram/mime_types.py
pyrogram/scaffold.py
pyrogram/sync.py
pyrogram/syncer.py
pyrogram/utils.py
pyrogram/connection/__init__.py
pyrogram/connection/connection.py
pyrogram/connection/transport/__init__.py
pyrogram/connection/transport/tcp/__init__.py
pyrogram/connection/transport/tcp/tcp.py
pyrogram/connection/transport/tcp/tcp_abridged.py
pyrogram/connection/transport/tcp/tcp_abridged_o.py
pyrogram/connection/transport/tcp/tcp_full.py
pyrogram/connection/transport/tcp/tcp_intermediate.py
pyrogram/connection/transport/tcp/tcp_intermediate_o.py
pyrogram/crypto/__init__.py
pyrogram/crypto/aes.py
pyrogram/crypto/mtproto.py
pyrogram/crypto/prime.py
pyrogram/crypto/rsa.py
pyrogram/errors/__init__.py
pyrogram/errors/rpc_error.py
pyrogram/handlers/__init__.py
pyrogram/handlers/callback_query_handler.py
pyrogram/handlers/chat_member_updated_handler.py
pyrogram/handlers/chosen_inline_result_handler.py
pyrogram/handlers/deleted_messages_handler.py
pyrogram/handlers/disconnect_handler.py
pyrogram/handlers/handler.py
pyrogram/handlers/inline_query_handler.py
pyrogram/handlers/message_handler.py
pyrogram/handlers/poll_handler.py
pyrogram/handlers/raw_update_handler.py
pyrogram/handlers/user_status_handler.py
pyrogram/methods/__init__.py
pyrogram/methods/advanced/__init__.py
pyrogram/methods/advanced/resolve_peer.py
pyrogram/methods/advanced/save_file.py
pyrogram/methods/advanced/send.py
pyrogram/methods/auth/__init__.py
pyrogram/methods/auth/accept_terms_of_service.py
pyrogram/methods/auth/check_password.py
pyrogram/methods/auth/connect.py
pyrogram/methods/auth/disconnect.py
pyrogram/methods/auth/get_password_hint.py
pyrogram/methods/auth/initialize.py
pyrogram/methods/auth/log_out.py
pyrogram/methods/auth/recover_password.py
pyrogram/methods/auth/resend_code.py
pyrogram/methods/auth/send_code.py
pyrogram/methods/auth/send_recovery_code.py
PyrogramPlus-1.2.22.dist-info/COPYING
PyrogramPlus-1.2.22.dist-info/COPYING.lesser
PyrogramPlus-1.2.22.dist-info/METADATA
PyrogramPlus-1.2.22.dist-info/NOTICE
PyrogramPlus-1.2.22.dist-info/WHEEL
PyrogramPlus-1.2.22.dist-info/top_level.txt
PyrogramPlus-1.2.22.dist-info/RECORD
